{"py/object": "rasa.core.featurizers.tracker_featurizers.IntentMaxHistoryTrackerFeaturizer", "state_featurizer": {"py/object": "rasa.core.featurizers.single_state_featurizer.IntentTokenizerSingleStateFeaturizer", "_default_feature_states": {"intent": {"affirm": 0, "asking_for_complaint": 1, "back": 2, "bakery": 3, "bot_challenge": 4, "buy": 5, "checkout": 6, "contact": 7, "deny": 8, "drinks": 9, "goodbye": 10, "greet": 11, "list_bakery": 12, "list_drinks": 13, "making_complaint": 14, "nlu_fallback": 15, "number": 16, "offers": 17, "order_bakery": 18, "order_drinks": 19, "order_food": 20, "order_general": 21, "out_of_scope": 22, "provide_size": 23, "restart": 24, "session_start": 25}, "action_name": {"action_listen": 0, "action_restart": 1, "action_session_start": 2, "action_default_fallback": 3, "action_deactivate_loop": 4, "action_revert_fallback_events": 5, "action_default_ask_affirmation": 6, "action_default_ask_rephrase": 7, "action_two_stage_fallback": 8, "action_unlikely_intent": 9, "action_back": 10, "...": 11, "action_extract_slots": 12, "action_bakery_order": 13, "action_size": 14, "action_drinks_order": 15, "action_checkout": 16, "utter_action_drinks_order": 17, "utter_ask_for_size": 18, "utter_asking_for_complaint": 19, "utter_buy": 20, "utter_contact": 21, "utter_did_that_help": 22, "utter_goodbye": 23, "utter_greet": 24, "utter_iamabot": 25, "utter_list_bakery": 26, "utter_list_drinks": 27, "utter_list_offers": 28, "utter_order": 29, "utter_register_complaint": 30}, "entities": {"bakery": 0, "bill": 1, "drinks": 2, "number": 3, "size": 4}, "slots": {"number_0": 0, "bakery_0": 1, "bill_0": 2}, "active_loop": {}}, "action_texts": [], "entity_tag_specs": null}, "max_history": 5, "remove_duplicates": true}